velodyne_decoder/pcap.py
velodyne_decoder/__init__.py
velodyne_decoder/hdl64e.py
velodyne_decoder/velodyne_decoder_pylib.cpython-38-x86_64-linux-gnu.so
velodyne_decoder/util.py
velodyne_decoder/bag.py
velodyne_decoder/calibrations/HDL-32E.yml
velodyne_decoder/calibrations/HDL-64E_S3-VeloView.yml
velodyne_decoder/calibrations/VLP-32B.yml
velodyne_decoder/calibrations/HDL-64E_S1-utexas.yml
velodyne_decoder/calibrations/__init__.py
velodyne_decoder/calibrations/HDL-64E_S2.1-sztaki.yml
velodyne_decoder/calibrations/Puck Hi-Res.yml
velodyne_decoder/calibrations/VLP-16.yml
velodyne_decoder/calibrations/Alpha Prime.yml
velodyne_decoder/calibrations/VLP-32C.yml
velodyne_decoder/calibrations/VLP-32A.yml
velodyne_decoder/calibrations/HDL-64E_S3-xiesc.yml
velodyne_decoder-3.1.0.dist-info/METADATA
velodyne_decoder-3.1.0.dist-info/RECORD
velodyne_decoder-3.1.0.dist-info/WHEEL
velodyne_decoder-3.1.0.dist-info/entry_points.txt
velodyne_decoder-3.1.0.dist-info/licenses/LICENSE
