Metadata-Version: 2.1
Name: velodyne-decoder
Version: 3.1.0
Summary: Decoder for raw Velodyne packet data
Keywords: Velodyne,pointcloud,PCL
Author-Email: Martin Valgur <martin.valgur@gmail.com>
License: BSD-3-Clause
Classifier: License :: OSI Approved :: BSD License
Classifier: Programming Language :: Python :: 3
Classifier: Operating System :: OS Independent
Project-URL: Homepage, https://github.com/valgur/velodyne_decoder
Project-URL: Bug reports, https://github.com/valgur/velodyne_decoder/issues
Project-URL: Source, https://github.com/valgur/velodyne_decoder
Requires-Python: >=3.8
Requires-Dist: numpy
Requires-Dist: importlib_resources
Requires-Dist: dpkt
Requires-Dist: pyyaml
